midea/__init__.py
midea/client.py
midea/cloud.py
midea/command.py
midea/crc8.py
midea/device.py
midea/packet_builder.py
midea/security.py
midea_andersonshatch-0.1.13.dist-info/LICENSE
midea_andersonshatch-0.1.13.dist-info/METADATA
midea_andersonshatch-0.1.13.dist-info/WHEEL
midea_andersonshatch-0.1.13.dist-info/top_level.txt
midea_andersonshatch-0.1.13.dist-info/RECORD
