Metadata-Version: 2.1
Name: midea-andersonshatch
Version: 0.1.13
Summary: A library to control Midea appliances via the cloud API
Home-page: https://github.com/andersonshatch/midea-ac-lib
Author: NeoAcheron, andersonshatch
Author-email: master@neoacheron.com, hello@andersonshatch.com
License: UNKNOWN
Platform: UNKNOWN
Classifier: Programming Language :: Python :: 3
Classifier: License :: OSI Approved :: MIT License
Classifier: Operating System :: OS Independent
